pyairly.py
pyairly-1.0.dist-info/metadata.json
pyairly-1.0.dist-info/RECORD
pyairly-1.0.dist-info/WHEEL
pyairly-1.0.dist-info/METADATA
pyairly-1.0.dist-info/top_level.txt
pyairly-1.0.dist-info/LICENSE.txt
pyairly-1.0.dist-info/DESCRIPTION.rst
