Metadata-Version: 2.0
Name: pyairly
Version: 1.0
Summary: UNKNOWN
Home-page: https://github.com/lemonov/PyAirly
License: Apache 2.0
Platform: UNKNOWN
Requires-Python: >=3
Requires-Dist: requests
